modu_muse/__init__.py
modu_muse/pipeline.py
modu_muse/projector.py
modu_muse/utils.py
modu_muse/models/__init__.py
modu_muse/models/llm.py
modu_muse/models/vision.py
modu_muse-0.1.5.dist-info/METADATA
modu_muse-0.1.5.dist-info/WHEEL
modu_muse-0.1.5.dist-info/top_level.txt
modu_muse-0.1.5.dist-info/RECORD
