Metadata-Version: 2.4
Name: modu-muse
Version: 0.1.5
Summary: Modular multimodal pipeline for vision-to-LLM integration
Home-page: https://github.com/ELkarousWissem/ModuMuse
Author: Wissem Elkarous
Author-email: karouswissem@gmail.com
Classifier: Programming Language :: Python :: 3
Classifier: License :: OSI Approved :: MIT License
Classifier: Operating System :: OS Independent
Requires-Python: >=3.8
Requires-Dist: transformers
Requires-Dist: torch
Requires-Dist: Pillow
Dynamic: author
Dynamic: author-email
Dynamic: classifier
Dynamic: description
Dynamic: description-content-type
Dynamic: home-page
Dynamic: requires-dist
Dynamic: requires-python
Dynamic: summary
